carnival_contrib/__init__.py
carnival_contrib/apt.py
carnival_contrib/caddy/Caddyfile
carnival_contrib/caddy/__init__.py
carnival_contrib/caddy/caddy.service
carnival_contrib/docker.py
carnival_contrib/docker_compose.py
carnival_contrib/py.typed
carnival_contrib/ssh.py
carnival_contrib/systemd.py
carnival_contrib-3.0.0.dist-info/LICENSE
carnival_contrib-3.0.0.dist-info/WHEEL
carnival_contrib-3.0.0.dist-info/METADATA
carnival_contrib-3.0.0.dist-info/RECORD
