Metadata-Version: 2.1
Name: carnival-contrib
Version: 3.0.0
Summary: Carnival community receipts
License: MIT
Author: Dmirty Simonov
Author-email: demalf@gmail.com
Requires-Python: >=3.8,<4.0
Classifier: License :: OSI Approved :: MIT License
Classifier: Programming Language :: Python :: 3
Classifier: Programming Language :: Python :: 3.8
Classifier: Programming Language :: Python :: 3.9
Requires-Dist: carnival (>=3.0.0)
